TenGiphPy/__init__.py
TenGiphPy-2.5.0.dist-info/LICENSE
TenGiphPy-2.5.0.dist-info/METADATA
TenGiphPy-2.5.0.dist-info/WHEEL
TenGiphPy-2.5.0.dist-info/top_level.txt
TenGiphPy-2.5.0.dist-info/RECORD
